rubycond/rubycond.py
rubycond/subs/Equations_RubySam_Scale.py
rubycond/subs/Init_file_class.py
rubycond/subs/Logger_class.py
rubycond/subs/__init__.py
rubycond/subs/logo_CP.jpg
rubycond/subs/logo_IMPMC.jpg
rubycond/subs/rubycond_calibrator.py
rubycond-0.1.2.dist-info/METADATA
rubycond-0.1.2.dist-info/WHEEL
rubycond-0.1.2.dist-info/entry_points.txt
rubycond-0.1.2.dist-info/RECORD
