Metadata-Version: 2.1
Name: rubycond
Version: 0.1.2
Summary: Pressure by Ruby Luminescence (PRL) software to determine pressure in diamond anvil cell experiments
License: GPL-3.0-or-later
Author: Yiuri GARINO
Author-email: yiuri.garino@cnrs.fr
Requires-Python: >=3.9,<4.0
Classifier: License :: OSI Approved :: GNU General Public License v3 or later (GPLv3+)
Classifier: Programming Language :: Python :: 3
Classifier: Programming Language :: Python :: 3.9
Classifier: Programming Language :: Python :: 3.10
Classifier: Programming Language :: Python :: 3.11
Classifier: Programming Language :: Python :: 3.12
Requires-Dist: configparser (>=6.0.0,<7.0.0)
Requires-Dist: lmfit (>=1.2.2,<2.0.0)
Requires-Dist: matplotlib (>=3.8.2,<4.0.0)
Requires-Dist: pathlib (>=1.0,<2.0)
Requires-Dist: pillow (>=10.1.0,<11.0.0)
